{
    "deviation": -0.00390625, 
    "lanes": [
        {
            "c3": 6.7651244449000165e-06, 
            "c2": -0.00045800661999999964, 
            "c1": -0.015706839999996447, 
            "c0": -1.6328125
        }, 
        {
            "c3": 2.440062406599999e-06, 
            "c2": -8.984349999999891e-05, 
            "c1": -0.008870919999999671, 
            "c0": 1.625
        }, 
        {
            "c3": -2.739899981701009e-12, 
            "c2": 2.000000165480742e-11, 
            "c1": -0.04402707999999933, 
            "c0": -3.15234375
        }, 
        {
            "c3": -2.739899981701009e-12, 
            "c2": -0.00421873918, 
            "c1": 0.11808187999999831, 
            "c0": 3.4609375
        }
    ], 
    "decision": 4, 
    "ax": -0.08217951500130424, 
    "ay": -0.22932677953252442, 
    "objects": [
        {
            "theta": 6.287312110153048, 
            "age": 176, 
            "v": 0.04968535249349606, 
            "l": 4.228339, 
            "value": 29.23858249200327, 
            "reliability": 5, 
            "w": 2.220225, 
            "ax": 0.01099717032530036, 
            "y": -0.6610962282057532, 
            "x": -5.366706091175051, 
            "omega": 0.06155930348142688, 
            "id": 47
        }, 
        {
            "theta": 3.108779418425248, 
            "age": 14, 
            "v": 16.788344390670865, 
            "l": 4.216033, 
            "value": 52.10743348303827, 
            "reliability": 5, 
            "w": 2.048635, 
            "ax": 0.1971542851378107, 
            "y": 7.216841446136158, 
            "x": -0.1569491139498549, 
            "omega": 0.2724804111572216, 
            "id": 61
        }, 
        {
            "theta": -0.029659672609517383, 
            "age": 258, 
            "v": 0.04810096457443331, 
            "l": 4.240995, 
            "value": 136.80824517020466, 
            "reliability": 5, 
            "w": 2.157749, 
            "ax": 0.002000775000270732, 
            "y": 0.6805918383856518, 
            "x": 11.676687883116834, 
            "omega": 0.03508040247033101, 
            "id": 39
        }
    ], 
    "is_tunnel": false, 
    "v": 0.019999999552965164, 
    "y": 126.7101106, 
    "x": 37.3633656, 
    "omega": 0.010573608843207731, 
    "theta": 3.7522834547364083
}