{
    "deviation": 0.626953125, 
    "lanes": [
        {
            "c3": -8.165839077499987e-06, 
            "c2": -0.000693357579999998, 
            "c1": 0.02530868000000197, 
            "c0": -0.9921875
        }, 
        {
            "c3": -8.165839077499987e-06, 
            "c2": -0.000693357579999998, 
            "c1": 0.02530868000000197, 
            "c0": 2.24609375
        }, 
        {
            "c3": -2.739899981701009e-12, 
            "c2": 2.000000165480742e-11, 
            "c1": -0.05086299999999966, 
            "c0": -4.52734375
        }, 
        {
            "c3": -2.739899981701009e-12, 
            "c2": 2.000000165480742e-11, 
            "c1": -0.030355239999998673, 
            "c0": 2.81640625
        }
    ], 
    "decision": 1, 
    "ax": 0.9449203807486958, 
    "ay": 0.29600600794747556, 
    "objects": [
        {
            "theta": 6.1163791756989685, 
            "age": 644, 
            "v": -0.6672074257401386, 
            "l": 4.228339, 
            "value": 127.70327001849142, 
            "reliability": 5, 
            "w": 2.220225, 
            "ax": -0.246800343883931, 
            "y": 3.3883976316391755, 
            "x": -10.780632240661651, 
            "omega": 0.008554501167468195, 
            "id": 47
        }, 
        {
            "theta": -0.09842664440574778, 
            "age": 146, 
            "v": 6.821310347514345, 
            "l": 4.171403, 
            "value": 316.10228695909285, 
            "reliability": 5, 
            "w": 2.145493, 
            "ax": 0.7395368090183434, 
            "y": 0.1403282508659636, 
            "x": 17.778711847068724, 
            "omega": 0.00647838171763653, 
            "id": 71
        }
    ], 
    "is_tunnel": false, 
    "v": 6.020008286568279, 
    "y": 126.7121179, 
    "x": 37.3616428, 
    "omega": 0.014762399047994122, 
    "theta": 2.206619778622753
}