{
    "deviation": 0.21484375, 
    "lanes": [
        {
            "c3": 2.948566998460002e-05, 
            "c2": -0.0013437465399999994, 
            "c1": -0.0059412399999985155, 
            "c0": -1.4140625
        }, 
        {
            "c3": 2.4069097888400012e-05, 
            "c2": -0.0019013623000000007, 
            "c1": 0.008707160000000158, 
            "c0": 1.84375
        }, 
        {
            "c3": -2.739899981701009e-12, 
            "c2": 2.000000165480742e-11, 
            "c1": -0.006917799999996532, 
            "c0": -3.57421875
        }, 
        {
            "c3": -2.739899981701009e-12, 
            "c2": 2.000000165480742e-11, 
            "c1": -0.0059412399999985155, 
            "c0": 4.859375
        }
    ], 
    "decision": 1, 
    "ax": 0.2378431893586958, 
    "ay": 0.1408444251474756, 
    "objects": [
        {
            "theta": 3.287609346317368, 
            "age": 25, 
            "v": -0.157919496776815, 
            "l": 4.306167, 
            "value": 27.800267431046176, 
            "reliability": 5, 
            "w": 2.243144, 
            "ax": -1.8178167641598695, 
            "y": 4.054678500646455, 
            "x": -3.3704376106733664, 
            "omega": 0.11166214738889692, 
            "id": 116
        }, 
        {
            "theta": -0.03176082352832256, 
            "age": 307, 
            "v": 14.01073594524782, 
            "l": 4.22529, 
            "value": 29.305967690101507, 
            "reliability": 5, 
            "w": 2.108433, 
            "ax": 0.48592402166709714, 
            "y": -3.1017337265406106, 
            "x": 4.436802404856678, 
            "omega": 0.03904556342825025, 
            "id": 91
        }, 
        {
            "theta": 3.0435476802195733, 
            "age": 28, 
            "v": -1.9645592636760623, 
            "l": 4.409017, 
            "value": 50.67619657703553, 
            "reliability": 5, 
            "w": 2.108968, 
            "ax": -1.3517396587142614, 
            "y": 3.538677264711307, 
            "x": 6.17688916795913, 
            "omega": 0.07079334950972956, 
            "id": 115
        }, 
        {
            "theta": 3.1779693180035786, 
            "age": 11, 
            "v": 0.8647305224734986, 
            "l": 4.350806, 
            "value": 256.7436123459491, 
            "reliability": 5, 
            "w": 2.013458, 
            "ax": -0.9808032767971397, 
            "y": 5.008229062207152, 
            "x": 15.22042226767749, 
            "omega": 0.9504702518723167, 
            "id": 117
        }, 
        {
            "theta": 3.175367602521443, 
            "age": 4, 
            "v": 2.5456819826451764, 
            "l": 4.225216, 
            "value": 551.7478336014412, 
            "reliability": 4, 
            "w": 2.083834, 
            "ax": -0.7403374385715761, 
            "y": 5.223921359899938, 
            "x": 22.90105847394444, 
            "omega": 1.6940067893868551, 
            "id": 118
        }
    ], 
    "is_tunnel": false, 
    "v": 11.69006801474184, 
    "y": 126.7187519, 
    "x": 37.3632051, 
    "omega": 0.019649320953578246, 
    "theta": 0.6496115688975782
}