{
    "deviation": 0.12109375, 
    "lanes": [
        {
            "c3": 1.6801031854000005e-06, 
            "c2": 3.9062599999986625e-06, 
            "c1": -0.008870919999999671, 
            "c0": -1.54296875
        }, 
        {
            "c3": 2.868446132000212e-07, 
            "c2": 9.667945999999872e-05, 
            "c1": -0.016683399999998016, 
            "c0": 1.78515625
        }, 
        {
            "c3": -2.739899981701009e-12, 
            "c2": 0.0005205064999999967, 
            "c1": -0.058675479999998004, 
            "c0": -2.86328125
        }, 
        {
            "c3": -2.739899981701009e-12, 
            "c2": 2.000000165480742e-11, 
            "c1": -0.007894359999998102, 
            "c0": 5.35546875
        }
    ], 
    "decision": 1, 
    "ax": -0.010823101191304252, 
    "ay": 0.0832129801074756, 
    "objects": [
        {
            "theta": 0.07546554300954267, 
            "age": 51, 
            "v": 0.6037844196296582, 
            "l": 4.231146, 
            "value": 19.591165726316426, 
            "reliability": 5, 
            "w": 2.019333, 
            "ax": 0.04575925194578673, 
            "y": 3.571137071180213, 
            "x": 2.6149848460667675, 
            "omega": 0.05916645028859588, 
            "id": 54
        }, 
        {
            "theta": 0.0175308973680093, 
            "age": 27, 
            "v": -0.9898656119465388, 
            "l": 4.55578, 
            "value": 61.607185304893456, 
            "reliability": 5, 
            "w": 2.048137, 
            "ax": -0.09018769561575019, 
            "y": 6.637002478511087, 
            "x": -4.190153148171454, 
            "omega": 0.024780857071564983, 
            "id": 60
        }, 
        {
            "theta": 0.03454525399881711, 
            "age": 58, 
            "v": -0.3136839286202688, 
            "l": 4.201142, 
            "value": 99.01913821210978, 
            "reliability": 5, 
            "w": 2.077341, 
            "ax": -0.11443061470262686, 
            "y": 3.3474536528300636, 
            "x": -9.370896021953527, 
            "omega": 0.020766423982993134, 
            "id": 52
        }, 
        {
            "theta": 0.0342076199504981, 
            "age": 23, 
            "v": -0.5706770910361355, 
            "l": 4.252116, 
            "value": 113.94296775419889, 
            "reliability": 5, 
            "w": 2.05218, 
            "ax": -0.41228414751347225, 
            "y": 4.290930076464653, 
            "x": 9.77399032294845, 
            "omega": 0.0833355552800698, 
            "id": 62
        }, 
        {
            "theta": 0.042847023268731764, 
            "age": 22, 
            "v": -0.530056428265721, 
            "l": 4.2441, 
            "value": 267.1711477161665, 
            "reliability": 5, 
            "w": 1.992582, 
            "ax": -0.5859066404917729, 
            "y": 4.044410890508147, 
            "x": 15.837104794276813, 
            "omega": 0.136927257732877, 
            "id": 63
        }, 
        {
            "theta": 0.11818799999999996, 
            "age": 1, 
            "v": 0.5121591160992509, 
            "l": 4.198579, 
            "value": 561.584032158586, 
            "reliability": 1, 
            "w": 2.05978, 
            "ax": -0.3754843498126111, 
            "y": 4.642765, 
            "x": 23.238519, 
            "omega": 2.0468725396877026, 
            "id": 66
        }, 
        {
            "theta": 0.04602122806199052, 
            "age": 30, 
            "v": 5.232787908235171, 
            "l": 4.168771, 
            "value": 1145.1670806825368, 
            "reliability": 5, 
            "w": 2.161834, 
            "ax": 0.21497511835838776, 
            "y": 1.782970846775512, 
            "x": 33.79331436308202, 
            "omega": 0.05036511953858605, 
            "id": 59
        }
    ], 
    "is_tunnel": false, 
    "v": 6.4303808435019185, 
    "y": 126.7117992, 
    "x": 37.3618591, 
    "omega": 0.016158662449589585, 
    "theta": 2.2193607407518554
}