{
    "deviation": -0.548828125, 
    "lanes": [
        {
            "c3": 4.5523020067000095e-06, 
            "c2": -7.617165999999898e-05, 
            "c1": -0.023519319999998345, 
            "c0": -1.66796875
        }, 
        {
            "c3": 4.5523020067000095e-06, 
            "c2": -7.617165999999898e-05, 
            "c1": -0.023519319999998345, 
            "c0": 0.5703125
        }, 
        {
            "c3": -2.739899981701009e-12, 
            "c2": 2.000000165480742e-11, 
            "c1": -8.187999999975659e-05, 
            "c0": -2.1953125
        }, 
        {
            "c3": -2.739899981701009e-12, 
            "c2": 2.000000165480742e-11, 
            "c1": -0.0059412399999985155, 
            "c0": 2.33203125
        }
    ], 
    "decision": 1, 
    "ax": 0.6292223075286957, 
    "ay": -0.0342665040125244, 
    "objects": [
        {
            "theta": -0.06500081538816099, 
            "age": 541, 
            "v": 11.183960028836074, 
            "l": 4.216399, 
            "value": 534.4421769203964, 
            "reliability": 5, 
            "w": 2.205615, 
            "ax": 0.8846383049295282, 
            "y": -2.052195810191635, 
            "x": 23.026738138021813, 
            "omega": 0.008721607971127943, 
            "id": 2
        }, 
        {
            "theta": -0.07168653000905212, 
            "age": 303, 
            "v": 12.264247207375645, 
            "l": 4.450777, 
            "value": 1275.9932717318616, 
            "reliability": 5, 
            "w": 2.068232, 
            "ax": 0.7312437743775834, 
            "y": -5.415236042815812, 
            "x": 35.308192963283325, 
            "omega": 0.007536841341104203, 
            "id": 4
        }
    ], 
    "is_tunnel": false, 
    "v": 10.535487382119786, 
    "y": 126.6846616, 
    "x": 37.3870717, 
    "omega": 0.010573608843207731, 
    "theta": 1.7736036338135373
}