{
    "deviation": 0.173828125, 
    "lanes": [
        {
            "c3": -4.3586170499998965e-07, 
            "c2": -1.7578060000002227e-05, 
            "c1": -0.004964679999996946, 
            "c0": -1.5625
        }, 
        {
            "c3": -4.3586170499998965e-07, 
            "c2": -1.7578060000002227e-05, 
            "c1": -0.004964679999996946, 
            "c0": 1.91015625
        }, 
        {
            "c3": -2.739899981701009e-12, 
            "c2": 2.000000165480742e-11, 
            "c1": -0.004964679999996946, 
            "c0": -4.95703125
        }, 
        {
            "c3": -2.739899981701009e-12, 
            "c2": 2.000000165480742e-11, 
            "c1": -0.004964679999996946, 
            "c0": 5.69921875
        }
    ], 
    "decision": 1, 
    "ax": 1.275754662958696, 
    "ay": -0.00988396957252441, 
    "objects": [
        {
            "theta": 0.03983117879427302, 
            "age": 20, 
            "v": 25.555889646878942, 
            "l": 4.275894, 
            "value": 31.29242378647475, 
            "reliability": 5, 
            "w": 2.116234, 
            "ax": 0.07518979207728962, 
            "y": 3.264120245276932, 
            "x": 4.542900264241777, 
            "omega": 0.09415366385790461, 
            "id": 40
        }, 
        {
            "theta": 0.03184052001616305, 
            "age": 75, 
            "v": 23.783392202456586, 
            "l": 4.766594, 
            "value": 765.2968229247679, 
            "reliability": 5, 
            "w": 2.061957, 
            "ax": 0.08487532249352682, 
            "y": 8.739017269813552, 
            "x": 26.247407492601404, 
            "omega": -0.00722059229296745, 
            "id": 37
        }
    ], 
    "is_tunnel": false, 
    "v": 18.570042775009973, 
    "y": 126.8905731, 
    "x": 37.413711, 
    "omega": 0.002894160134432681, 
    "theta": 3.576703108280247
}