{
    "deviation": -0.0078125, 
    "lanes": [
        {
            "c3": -3.3527886689999303e-07, 
            "c2": 0.000663084260000002, 
            "c1": 0.0038243600000029687, 
            "c0": -1.625
        }, 
        {
            "c3": -3.3527886689999303e-07, 
            "c2": 0.000663084260000002, 
            "c1": 0.0038243600000029687, 
            "c0": 1.609375
        }, 
        {
            "c3": -2.739899981701009e-12, 
            "c2": 2.000000165480742e-11, 
            "c1": 0.01456652000000247, 
            "c0": -5.01171875
        }, 
        {
            "c3": -2.739899981701009e-12, 
            "c2": 2.000000165480742e-11, 
            "c1": 0.011636840000001314, 
            "c0": 3.5
        }
    ], 
    "decision": 1, 
    "ax": 0.7632858728686958, 
    "ay": -0.48201850009252445, 
    "objects": [
        {
            "theta": 0.15671060978639947, 
            "age": 44, 
            "v": 22.16527361923533, 
            "l": 4.312689, 
            "value": 49.1880825303497, 
            "reliability": 5, 
            "w": 2.251789, 
            "ax": -0.6833676944145919, 
            "y": 6.86117297945948, 
            "x": -1.45340561313242, 
            "omega": -0.04598221201498112, 
            "id": 59
        }, 
        {
            "theta": 0.09105327314301322, 
            "age": 120, 
            "v": 21.621014288805373, 
            "l": 4.180366, 
            "value": 327.753922639504, 
            "reliability": 5, 
            "w": 2.165404, 
            "ax": -0.035811433861833206, 
            "y": -1.8276748856442135, 
            "x": 18.011483202443085, 
            "omega": -0.06437674416911994, 
            "id": 56
        }, 
        {
            "theta": 0.20452245297110505, 
            "age": 3, 
            "v": 24.29642854279428, 
            "l": 4.309755, 
            "value": 439.48662768632465, 
            "reliability": 3, 
            "w": 2.19551, 
            "ax": 0.5417035940025622, 
            "y": -6.612604007658017, 
            "x": 19.893720012210633, 
            "omega": 1.954032524857229, 
            "id": 66
        }, 
        {
            "theta": 0.07295550435797277, 
            "age": 85, 
            "v": 24.02553373128784, 
            "l": 4.181533, 
            "value": 666.6055116525681, 
            "reliability": 5, 
            "w": 2.164084, 
            "ax": -0.22081344434254513, 
            "y": 4.758209586718674, 
            "x": 25.3764645524436, 
            "omega": -0.032807097203985044, 
            "id": 57
        }, 
        {
            "theta": 0.027962704422666074, 
            "age": 9, 
            "v": 21.38747860894924, 
            "l": 4.200433, 
            "value": 1149.5610295678782, 
            "reliability": 5, 
            "w": 2.121183, 
            "ax": 0.07452579176717818, 
            "y": 8.026928225856167, 
            "x": 32.9413031439989, 
            "omega": 0.6467833120268653, 
            "id": 64
        }
    ], 
    "is_tunnel": false, 
    "v": 21.83122503812921, 
    "y": 126.8860661, 
    "x": 37.4073892, 
    "omega": -0.030616161503858444, 
    "theta": 4.016526292835706
}