{
    "deviation": 0.154296875, 
    "lanes": [
        {
            "c3": -1.0617104753999837e-06, 
            "c2": -7.617165999999898e-05, 
            "c1": 0.0008946800000018129, 
            "c0": -1.5234375
        }, 
        {
            "c3": -1.0617104753999837e-06, 
            "c2": -7.617165999999898e-05, 
            "c1": 0.0008946800000018129, 
            "c0": 1.83203125
        }, 
        {
            "c3": -2.739899981701009e-12, 
            "c2": 2.000000165480742e-11, 
            "c1": 0.0018712399999998297, 
            "c0": -4.8515625
        }, 
        {
            "c3": -2.739899981701009e-12, 
            "c2": 2.000000165480742e-11, 
            "c1": -8.187999999975659e-05, 
            "c0": 3.3828125
        }
    ], 
    "decision": 1, 
    "ax": 0.2551417139186957, 
    "ay": 0.03888109930747555, 
    "objects": [
        {
            "theta": 0.035171473645094604, 
            "age": 85, 
            "v": 15.417800651669092, 
            "l": 4.26889, 
            "value": 12.691196507802616, 
            "reliability": 5, 
            "w": 2.212531, 
            "ax": 0.27767365722404663, 
            "y": -3.4421806691566657, 
            "x": -0.9179263307514303, 
            "omega": -0.016909124621080535, 
            "id": 76
        }, 
        {
            "theta": 0.06144753987382203, 
            "age": 105, 
            "v": 16.957839829548956, 
            "l": 4.176253, 
            "value": 250.3382696788458, 
            "reliability": 5, 
            "w": 2.151671, 
            "ax": -0.09231679241003364, 
            "y": 0.09922329640060727, 
            "x": -15.821770584112803, 
            "omega": 0.0025564136721673535, 
            "id": 72
        }, 
        {
            "theta": 0.07944881532502643, 
            "age": 64, 
            "v": 13.91562218484881, 
            "l": 4.176954, 
            "value": 318.2197244615412, 
            "reliability": 5, 
            "w": 2.164474, 
            "ax": -0.10153911845886124, 
            "y": -2.66090548053232, 
            "x": 17.639141319384407, 
            "omega": -0.019506636315173416, 
            "id": 77
        }, 
        {
            "theta": 0.04188544675546221, 
            "age": 252, 
            "v": 21.958347607900848, 
            "l": 4.312689, 
            "value": 1002.9521246937303, 
            "reliability": 5, 
            "w": 2.251789, 
            "ax": 0.21770817867721579, 
            "y": 4.540627233397122, 
            "x": 31.342221188375635, 
            "omega": -0.008349601722573907, 
            "id": 59
        }, 
        {
            "theta": 0.028500454403980083, 
            "age": 41, 
            "v": 23.032220912524444, 
            "l": 4.168972, 
            "value": 1891.5154815070262, 
            "reliability": 5, 
            "w": 2.078393, 
            "ax": 0.43523177795568857, 
            "y": 9.38842665478406, 
            "x": 42.466138586581735, 
            "omega": 0.007217181779365619, 
            "id": 78
        }
    ], 
    "is_tunnel": false, 
    "v": 17.387480289522124, 
    "y": 126.8821268, 
    "x": 37.405492, 
    "omega": -0.004785288574342369, 
    "theta": 4.202229314595257
}