{
    "deviation": 0.220703125, 
    "lanes": [
        {
            "c3": 6.742748044000072e-07, 
            "c2": 2.929681999999656e-05, 
            "c1": 0.035074280000003455, 
            "c0": -1.38671875
        }, 
        {
            "c3": -7.674125416999941e-07, 
            "c2": -3.222645999999968e-05, 
            "c1": 0.0321446000000023, 
            "c0": 1.828125
        }, 
        {
            "c3": -2.739899981701009e-12, 
            "c2": 2.000000165480742e-11, 
            "c1": 0.031168040000004282, 
            "c0": -4.9765625
        }, 
        {
            "c3": -2.739899981701009e-12, 
            "c2": 2.000000165480742e-11, 
            "c1": 0.033121160000000316, 
            "c0": 2.94140625
        }
    ], 
    "decision": 1, 
    "ax": 0.6984164057686958, 
    "ay": -0.14952939409252441, 
    "objects": [
        {
            "theta": -0.009237888185739904, 
            "age": 40, 
            "v": 24.086743025307474, 
            "l": 4.691, 
            "value": 109.34523726429299, 
            "reliability": 5, 
            "w": 2.201307, 
            "ax": 0.2475342448094695, 
            "y": 6.471554851685757, 
            "x": 8.213660272126887, 
            "omega": 0.001347408701645807, 
            "id": 6
        }, 
        {
            "theta": -0.034578240762630066, 
            "age": 75, 
            "v": 23.013599667144867, 
            "l": 4.176001, 
            "value": 416.8726607156347, 
            "reliability": 5, 
            "w": 2.182202, 
            "ax": 0.1662104602819075, 
            "y": 3.1521169106468445, 
            "x": 20.1726750753897, 
            "omega": 0.009936393790863765, 
            "id": 5
        }
    ], 
    "is_tunnel": false, 
    "v": 18.160891896065642, 
    "y": 126.89763, 
    "x": 37.4330696, 
    "omega": 0.02174371605597144, 
    "theta": 3.534815312758827
}