{
    "deviation": 0.146484375, 
    "lanes": [
        {
            "c3": 4.7683441850002086e-07, 
            "c2": 0.0006074203399999978, 
            "c1": 0.0038243600000029687, 
            "c0": -1.45703125
        }, 
        {
            "c3": -4.1723525349998225e-07, 
            "c2": 0.0007480449800000011, 
            "c1": -0.0010584399999977734, 
            "c0": 1.75
        }, 
        {
            "c3": -2.739899981701009e-12, 
            "c2": 2.000000165480742e-11, 
            "c1": 0.0048009200000009855, 
            "c0": -4.33984375
        }, 
        {
            "c3": -2.739899981701009e-12, 
            "c2": 2.000000165480742e-11, 
            "c1": 0.005777479999999002, 
            "c0": 5.53125
        }
    ], 
    "decision": 1, 
    "ax": 0.22054466479869578, 
    "ay": -0.3024743828525244, 
    "objects": [
        {
            "theta": 0.08892335553284644, 
            "age": 51, 
            "v": 25.38388527731524, 
            "l": 4.295943, 
            "value": 126.94188233480739, 
            "reliability": 5, 
            "w": 2.200888, 
            "ax": 0.20760929581022247, 
            "y": -6.873946620413827, 
            "x": 8.926967021027282, 
            "omega": -0.03147914629264156, 
            "id": 54
        }, 
        {
            "theta": -0.017301439092599284, 
            "age": 20, 
            "v": 24.501765669881465, 
            "l": 4.180366, 
            "value": 210.8759373412783, 
            "reliability": 5, 
            "w": 2.165404, 
            "ax": 0.7154890766663796, 
            "y": -5.213009761272704, 
            "x": -13.553614520494294, 
            "omega": 0.1225029973759208, 
            "id": 56
        }, 
        {
            "theta": 0.05969850495291283, 
            "age": 63, 
            "v": 26.001541010126378, 
            "l": 4.267436, 
            "value": 875.9365022574254, 
            "reliability": 5, 
            "w": 2.087878, 
            "ax": -0.01052138510308976, 
            "y": 8.058568446400677, 
            "x": 28.477991095793623, 
            "omega": -0.007880700051637463, 
            "id": 53
        }
    ], 
    "is_tunnel": false, 
    "v": 20.028113199218335, 
    "y": 126.8876261, 
    "x": 37.4087793, 
    "omega": -0.032012424905453904, 
    "theta": 3.726452390059294
}