{
    "deviation": -0.076171875, 
    "lanes": [
        {
            "c3": 1.2665713030002258e-07, 
            "c2": 4.492177999999847e-05, 
            "c1": 0.0038243600000029687, 
            "c0": -1.671875
        }, 
        {
            "c3": 1.2665713030002258e-07, 
            "c2": 4.492177999999847e-05, 
            "c1": 0.0038243600000029687, 
            "c0": 1.51953125
        }, 
        {
            "c3": -2.739899981701009e-12, 
            "c2": 2.000000165480742e-11, 
            "c1": 0.0048009200000009855, 
            "c0": -5.01171875
        }, 
        {
            "c3": -2.739899981701009e-12, 
            "c2": 2.000000165480742e-11, 
            "c1": 0.0008946800000018129, 
            "c0": 5.6796875
        }
    ], 
    "decision": 1, 
    "ax": -0.17515908451130424, 
    "ay": 0.03001472314747558, 
    "objects": [
        {
            "theta": 0.048904299700262235, 
            "age": 138, 
            "v": 18.87406416008064, 
            "l": 4.312689, 
            "value": 47.37625970460118, 
            "reliability": 5, 
            "w": 2.251789, 
            "ax": 0.4055314980033541, 
            "y": 6.430902374026805, 
            "x": -2.4535187711402555, 
            "omega": -0.027830760227422473, 
            "id": 59
        }, 
        {
            "theta": 0.11706546990778242, 
            "age": 61, 
            "v": 22.201587864770996, 
            "l": 4.181797, 
            "value": 85.53405179763936, 
            "reliability": 5, 
            "w": 2.142523, 
            "ax": -0.16763996473500392, 
            "y": 3.9611712752996406, 
            "x": 8.357222859621514, 
            "omega": 0.05390891749341004, 
            "id": 68
        }, 
        {
            "theta": 0.12454396739650116, 
            "age": 103, 
            "v": 16.651739932538508, 
            "l": 4.200433, 
            "value": 478.9000560799227, 
            "reliability": 5, 
            "w": 2.121183, 
            "ax": -0.5452799592964392, 
            "y": 8.532826975802463, 
            "x": 20.151697692277455, 
            "omega": 0.022562491549538433, 
            "id": 64
        }, 
        {
            "theta": 0.141037602933151, 
            "age": 52, 
            "v": 18.6745344466414, 
            "l": 4.163482, 
            "value": 483.48614638134376, 
            "reliability": 5, 
            "w": 2.201462, 
            "ax": 0.23004500361295918, 
            "y": -2.065806595617323, 
            "x": 21.891061863026373, 
            "omega": 0.0337238838908169, 
            "id": 69
        }, 
        {
            "theta": 0.13606825899724784, 
            "age": 214, 
            "v": 21.55659602598232, 
            "l": 4.180366, 
            "value": 1645.3145828814756, 
            "reliability": 5, 
            "w": 2.165404, 
            "ax": -0.25148079377236304, 
            "y": 2.143548812889481, 
            "x": 40.505799354761976, 
            "omega": 0.02139640601567299, 
            "id": 56
        }
    ], 
    "is_tunnel": false, 
    "v": 19.431212082571566, 
    "y": 126.8841817, 
    "x": 37.4064126, 
    "omega": 0.004290423536028144, 
    "theta": 4.194200682856996
}