{
    "deviation": 0.25390625, 
    "lanes": [
        {
            "c3": -1.1921202949998573e-07, 
            "c2": -9.765400000028013e-07, 
            "c1": -0.009847479999997688, 
            "c0": -1.41015625
        }, 
        {
            "c3": -1.1921202949998573e-07, 
            "c2": -9.765400000028013e-07, 
            "c1": -0.009847479999997688, 
            "c0": 1.91796875
        }, 
        {
            "c3": -2.739899981701009e-12, 
            "c2": 2.000000165480742e-11, 
            "c1": -0.0059412399999985155, 
            "c0": -3.078125
        }, 
        {
            "c3": -2.739899981701009e-12, 
            "c2": 2.000000165480742e-11, 
            "c1": -0.01473027999999843, 
            "c0": 5.47265625
        }
    ], 
    "decision": 1, 
    "ax": -1.0876562550513043, 
    "ay": 0.32260513642747557, 
    "objects": [
        {
            "theta": 8.368215067291503, 
            "age": 500, 
            "v": 9.950867013680384, 
            "l": 4.228339, 
            "value": 142.67235687601075, 
            "reliability": 5, 
            "w": 2.220225, 
            "ax": -0.2825723131784721, 
            "y": 2.6622517941320165, 
            "x": -11.644087437865263, 
            "omega": 2.1451094105059196, 
            "id": 47
        }, 
        {
            "theta": 0.16865304722252975, 
            "age": 2, 
            "v": 2.3534515141940062, 
            "l": 4.171403, 
            "value": 1458.4277904159762, 
            "reliability": 2, 
            "w": 2.145493, 
            "ax": -0.6992287006344855, 
            "y": 1.7696157141246487, 
            "x": 38.148345319820876, 
            "omega": 2.1221106169360957, 
            "id": 71
        }
    ], 
    "is_tunnel": false, 
    "v": 7.570006776677865, 
    "y": 126.7116511, 
    "x": 37.3619254, 
    "omega": 0.013715201496797525, 
    "theta": 2.1977185621533266
}