{
    "deviation": 0.234375, 
    "lanes": [
        {
            "c3": 1.825364848000177e-07, 
            "c2": -1.9531000000003185e-06, 
            "c1": -8.187999999975659e-05, 
            "c0": -1.4140625
        }, 
        {
            "c3": 1.825364848000177e-07, 
            "c2": -1.9531000000003185e-06, 
            "c1": -8.187999999975659e-05, 
            "c0": 1.8828125
        }, 
        {
            "c3": -2.739899981701009e-12, 
            "c2": 2.000000165480742e-11, 
            "c1": -0.0010584399999977734, 
            "c0": -3.16015625
        }, 
        {
            "c3": -2.739899981701009e-12, 
            "c2": 2.000000165480742e-11, 
            "c1": -0.002034999999999343, 
            "c0": 5.2578125
        }
    ], 
    "decision": 1, 
    "ax": -0.01731004790130425, 
    "ay": -0.00988396957252441, 
    "objects": [
        {
            "theta": -0.2171736456935961, 
            "age": 39, 
            "v": 4.347718818147699, 
            "l": 4.275893, 
            "value": 188.51585475590971, 
            "reliability": 5, 
            "w": 2.146348, 
            "ax": 0.30717157760049596, 
            "y": -1.4099729864221127, 
            "x": -13.657519208607017, 
            "omega": -1.0906001793362854, 
            "id": 87
        }, 
        {
            "theta": -0.0528510245894272, 
            "age": 92, 
            "v": 11.561861394990263, 
            "l": 4.567926, 
            "value": 297.8693189293175, 
            "reliability": 5, 
            "w": 2.525617, 
            "ax": 1.630799537044073, 
            "y": -8.099430364381433, 
            "x": 15.240359139529932, 
            "omega": -0.0031137787211285356, 
            "id": 85
        }, 
        {
            "theta": -0.004818635795039482, 
            "age": 92, 
            "v": 10.677238727219125, 
            "l": 4.203132, 
            "value": 1098.4540379644927, 
            "reliability": 5, 
            "w": 2.522838, 
            "ax": 1.6499077685859045, 
            "y": -3.151728690222382, 
            "x": 32.992736234324695, 
            "omega": 0.08262088248455862, 
            "id": 84
        }
    ], 
    "is_tunnel": false, 
    "v": 8.038985987541801, 
    "y": 126.7149988, 
    "x": 37.3607717, 
    "omega": 0.014762399047994122, 
    "theta": 0.9183922337572886
}