{
    "deviation": 0.0, 
    "lanes": [
        {
            "c3": -2.739899981701009e-12, 
            "c2": 2.000000165480742e-11, 
            "c1": -8.187999999975659e-05, 
            "c0": -1.875
        }, 
        {
            "c3": -2.739899981701009e-12, 
            "c2": 2.000000165480742e-11, 
            "c1": -8.187999999975659e-05, 
            "c0": 1.875
        }, 
        {
            "c3": -2.739899981701009e-12, 
            "c2": 2.000000165480742e-11, 
            "c1": -0.02156619999999876, 
            "c0": -2.609375
        }, 
        {
            "c3": -2.739899981701009e-12, 
            "c2": 0.01674800402, 
            "c1": -0.3672684399999966, 
            "c0": 2.3125
        }
    ], 
    "decision": 1, 
    "ax": 0.31568654987869577, 
    "ay": 1.3023397021074754, 
    "objects": [
        {
            "theta": -1.2387983984512192, 
            "age": 23, 
            "v": 1.1939696436845453, 
            "l": 4.203764, 
            "value": 133.77426814622964, 
            "reliability": 5, 
            "w": 2.173324, 
            "ax": -0.06242414406213813, 
            "y": 2.521292545483812, 
            "x": -11.287929484467796, 
            "omega": 0.07608642056405164, 
            "id": 24
        }
    ], 
    "is_tunnel": false, 
    "v": 4.010611154883268, 
    "y": 126.7235758, 
    "x": 37.364778, 
    "omega": 0.30902491093423806, 
    "theta": 2.462136103620133
}