{
    "deviation": 0.06640625, 
    "lanes": [
        {
            "c3": -1.3411319069998623e-07, 
            "c2": 3.9062599999986625e-06, 
            "c1": -0.004964679999996946, 
            "c0": -1.62109375
        }, 
        {
            "c3": -1.3411319069998623e-07, 
            "c2": 3.9062599999986625e-06, 
            "c1": -0.004964679999996946, 
            "c0": 1.75390625
        }, 
        {
            "c3": -2.739899981701009e-12, 
            "c2": 2.000000165480742e-11, 
            "c1": -0.004964679999996946, 
            "c0": -4.8828125
        }, 
        {
            "c3": -2.739899981701009e-12, 
            "c2": 2.000000165480742e-11, 
            "c1": -0.0059412399999985155, 
            "c0": 5.44921875
        }
    ], 
    "decision": 1, 
    "ax": 0.07350720603869576, 
    "ay": 0.2871396317874756, 
    "objects": [
        {
            "theta": 0.024539280699475197, 
            "age": 23, 
            "v": 27.580916423218984, 
            "l": 4.367855, 
            "value": 34.629680136633326, 
            "reliability": 5, 
            "w": 2.27287, 
            "ax": -0.0010563277766830192, 
            "y": 3.161880282705952, 
            "x": 4.963083035217994, 
            "omega": 0.05557546471908486, 
            "id": 74
        }, 
        {
            "theta": -0.11163813499475618, 
            "age": 119, 
            "v": 19.378498344481645, 
            "l": 4.162231, 
            "value": 204.94512586273308, 
            "reliability": 5, 
            "w": 2.136022, 
            "ax": -0.1340529528202594, 
            "y": -5.422139750161381, 
            "x": -13.249359471025494, 
            "omega": 0.018820046768121455, 
            "id": 63
        }, 
        {
            "theta": 0.11619676079899294, 
            "age": 7, 
            "v": 20.209785304735444, 
            "l": 4.215027, 
            "value": 1398.8306084408164, 
            "reliability": 5, 
            "w": 2.189974, 
            "ax": 0.11525979799109996, 
            "y": -2.074731614981148, 
            "x": 37.34335412314505, 
            "omega": 0.920429435969939, 
            "id": 75
        }
    ], 
    "is_tunnel": false, 
    "v": 21.230150271796678, 
    "y": 126.7866181, 
    "x": 37.3884085, 
    "omega": 0.01580959659919072, 
    "theta": 1.564338560625618
}