{
    "deviation": -0.03125, 
    "lanes": [
        {
            "c3": -1.452890615999934e-07, 
            "c2": 8.789060000000126e-06, 
            "c1": 0.0018712399999998297, 
            "c0": -1.75
        }, 
        {
            "c3": -1.452890615999934e-07, 
            "c2": 8.789060000000126e-06, 
            "c1": 0.0018712399999998297, 
            "c0": 1.6875
        }, 
        {
            "c3": -2.739899981701009e-12, 
            "c2": 2.000000165480742e-11, 
            "c1": -8.187999999975659e-05, 
            "c0": -4.96484375
        }, 
        {
            "c3": -2.739899981701009e-12, 
            "c2": 2.000000165480742e-11, 
            "c1": -8.187999999975659e-05, 
            "c0": 5.390625
        }
    ], 
    "decision": 1, 
    "ax": -0.11028961741130425, 
    "ay": 0.22507499866747557, 
    "objects": [
        {
            "theta": -0.13953434336767764, 
            "age": 152, 
            "v": 17.70866967908771, 
            "l": 4.162231, 
            "value": 319.9991887068152, 
            "reliability": 5, 
            "w": 2.136022, 
            "ax": -0.32282348448060727, 
            "y": -6.086304174096264, 
            "x": -16.821298707507502, 
            "omega": 0.026022619363954076, 
            "id": 63
        }, 
        {
            "theta": -0.021143728524241324, 
            "age": 56, 
            "v": 28.3869985885113, 
            "l": 4.367855, 
            "value": 740.8781036270049, 
            "reliability": 5, 
            "w": 2.27287, 
            "ax": 0.16751384174913114, 
            "y": 4.539253853188338, 
            "x": 26.837907483321416, 
            "omega": -0.00713395337539958, 
            "id": 74
        }
    ], 
    "is_tunnel": false, 
    "v": 21.41002086561679, 
    "y": 126.7874134, 
    "x": 37.3884135, 
    "omega": 0.0063848186384213405, 
    "theta": 1.5601498077050868
}