{
    "deviation": 0.041015625, 
    "lanes": [
        {
            "c3": -2.4959718999998336e-07, 
            "c2": 5.859380000000636e-06, 
            "c1": -0.008870919999999671, 
            "c0": -1.65234375
        }, 
        {
            "c3": -2.4959718999998336e-07, 
            "c2": 5.859380000000636e-06, 
            "c1": -0.008870919999999671, 
            "c0": 1.734375
        }, 
        {
            "c3": -2.739899981701009e-12, 
            "c2": 2.000000165480742e-11, 
            "c1": -0.003988119999998929, 
            "c0": -4.9609375
        }, 
        {
            "c3": -2.739899981701009e-12, 
            "c2": 2.000000165480742e-11, 
            "c1": -0.007894359999998102, 
            "c0": 5.36328125
        }
    ], 
    "decision": 1, 
    "ax": 0.27244023847869575, 
    "ay": 0.05218066354747555, 
    "objects": [
        {
            "theta": 0.06620734901056899, 
            "age": 2, 
            "v": 26.67630613189021, 
            "l": 4.262321, 
            "value": 226.22273509843015, 
            "reliability": 2, 
            "w": 2.155648, 
            "ax": 0.16517530802611635, 
            "y": 3.195160415341696, 
            "x": -14.697404023114546, 
            "omega": 2.1069147109047752, 
            "id": 95
        }, 
        {
            "theta": 0.06574409791030697, 
            "age": 55, 
            "v": 28.435666960725467, 
            "l": 4.158687, 
            "value": 670.112743591595, 
            "reliability": 5, 
            "w": 2.122655, 
            "ax": 0.3167800346551579, 
            "y": 5.556524463266451, 
            "x": 25.28315208752098, 
            "omega": -0.0344691880846805, 
            "id": 92
        }
    ], 
    "is_tunnel": false, 
    "v": 22.2601821688517, 
    "y": 126.7922569, 
    "x": 37.3884503, 
    "omega": 0.00987547714241, 
    "theta": 1.5704473195340418
}