{
    "deviation": 0.974609375, 
    "lanes": [
        {
            "c3": -1.9297031152999927e-06, 
            "c2": 2.5390579999999552e-05, 
            "c1": -0.15340179999999748, 
            "c0": -0.62890625
        }, 
        {
            "c3": -1.9297031152999927e-06, 
            "c2": 2.5390579999999552e-05, 
            "c1": -0.15340179999999748, 
            "c0": 2.578125
        }, 
        {
            "c3": -2.739899981701009e-12, 
            "c2": 9.76579999999172e-07, 
            "c1": -0.15047211999999988, 
            "c0": -4.2421875
        }, 
        {
            "c3": -2.739899981701009e-12, 
            "c2": 2.000000165480742e-11, 
            "c1": -0.1602377199999978, 
            "c0": 3.26953125
        }
    ], 
    "decision": 3, 
    "ax": -0.35463127682130424, 
    "ay": 0.5376147583074756, 
    "objects": [
        {
            "theta": 3.227502510393625, 
            "age": 39, 
            "v": -1.2986470459944053, 
            "l": 4.363729, 
            "value": 66.87769661514031, 
            "reliability": 5, 
            "w": 2.102414, 
            "ax": -0.7195886249630304, 
            "y": 6.835178805249621, 
            "x": 4.4897691828652695, 
            "omega": 0.008926759093710414, 
            "id": 3
        }, 
        {
            "theta": 3.2723633648294235, 
            "age": 50, 
            "v": -1.327040892742874, 
            "l": 4.225742, 
            "value": 270.52475425954543, 
            "reliability": 5, 
            "w": 2.121612, 
            "ax": -0.3868355707020993, 
            "y": 5.1469934595623, 
            "x": -15.621562424635005, 
            "omega": 0.009797032336278842, 
            "id": 2
        }, 
        {
            "theta": 3.2445582217630085, 
            "age": 29, 
            "v": -2.128846260314895, 
            "l": 4.192678, 
            "value": 502.22088505691966, 
            "reliability": 5, 
            "w": 2.279499, 
            "ax": -1.1342871080581598, 
            "y": 9.668155408615236, 
            "x": 20.21750865096349, 
            "omega": 0.06122256315584472, 
            "id": 4
        }
    ], 
    "is_tunnel": false, 
    "v": 7.690058574550029, 
    "y": 126.7246875, 
    "x": 37.3654367, 
    "omega": 0.08597183252936277, 
    "theta": 0.7780678124970052
}