{
    "deviation": 0.0, 
    "lanes": [
        {
            "c3": -2.739899981701009e-12, 
            "c2": 2.000000165480742e-11, 
            "c1": -8.187999999975659e-05, 
            "c0": -1.875
        }, 
        {
            "c3": -2.739899981701009e-12, 
            "c2": 2.000000165480742e-11, 
            "c1": -8.187999999975659e-05, 
            "c0": 1.875
        }, 
        {
            "c3": -2.739899981701009e-12, 
            "c2": 2.000000165480742e-11, 
            "c1": -0.003988119999998929, 
            "c0": -2.71875
        }, 
        {
            "c3": -2.739899981701009e-12, 
            "c2": 2.000000165480742e-11, 
            "c1": -0.034261479999997846, 
            "c0": 2.53125
        }
    ], 
    "decision": 1, 
    "ax": -1.6498583032513041, 
    "ay": -0.9497198425325245, 
    "objects": [
        {
            "theta": -0.4127949418739399, 
            "age": 26, 
            "v": 1.788167760173511, 
            "l": 4.263164, 
            "value": 123.18962306192203, 
            "reliability": 5, 
            "w": 2.630484, 
            "ax": -0.6519841907385904, 
            "y": 2.90181417676283, 
            "x": 10.71303400281453, 
            "omega": 0.3578185141092098, 
            "id": 0
        }
    ], 
    "is_tunnel": false, 
    "v": 5.410147719695602, 
    "y": 126.7238705, 
    "x": 37.3646783, 
    "omega": -0.04702225647260514, 
    "theta": 4.0139081391680485
}