{
    "deviation": 1.16796875, 
    "lanes": [
        {
            "c3": 5.960190490000676e-08, 
            "c2": 0.00025488217999999896, 
            "c1": 0.0321446000000023, 
            "c0": -0.62109375
        }, 
        {
            "c3": -5.103675109999922e-07, 
            "c2": 0.00014257778, 
            "c1": 0.03019147999999916, 
            "c0": 2.95703125
        }, 
        {
            "c3": -2.739899981701009e-12, 
            "c2": 0.0002626946599999999, 
            "c1": 0.03702739999999949, 
            "c0": -3.83984375
        }, 
        {
            "c3": -2.739899981701009e-12, 
            "c2": 2.000000165480742e-11, 
            "c1": 0.06046484000000163, 
            "c0": 3.75390625
        }
    ], 
    "decision": 1, 
    "ax": 0.3135242343086958, 
    "ay": -0.1672621464125244, 
    "objects": [
        {
            "theta": 0.03247977275466919, 
            "age": 70, 
            "v": 16.87338469666649, 
            "l": 4.159796, 
            "value": 39.61573345966636, 
            "reliability": 5, 
            "w": 2.152975, 
            "ax": 0.31609654860683234, 
            "y": -5.434209412302883, 
            "x": -3.175704885990687, 
            "omega": -0.005853353881748662, 
            "id": 29
        }, 
        {
            "theta": -0.030213141277611218, 
            "age": 28, 
            "v": 16.433309214428714, 
            "l": 4.227067, 
            "value": 655.3561676472242, 
            "reliability": 5, 
            "w": 2.451254, 
            "ax": -0.30341610236967714, 
            "y": -6.825285684241899, 
            "x": 24.673298177902904, 
            "omega": 0.03273715205470189, 
            "id": 30
        }
    ], 
    "is_tunnel": false, 
    "v": 22.490499987921194, 
    "y": 126.7471264, 
    "x": 37.385514, 
    "omega": -0.000596498369555977, 
    "theta": 1.027998956056271
}