{
    "deviation": -0.080078125, 
    "lanes": [
        {
            "c3": -2.671035884999984e-06, 
            "c2": -2.4413979999998725e-05, 
            "c1": -0.0030115599999973597, 
            "c0": -1.72265625
        }, 
        {
            "c3": -2.671035884999984e-06, 
            "c2": -2.4413979999998725e-05, 
            "c1": -0.0030115599999973597, 
            "c0": 1.5625
        }, 
        {
            "c3": -2.739899981701009e-12, 
            "c2": 2.000000165480742e-11, 
            "c1": -0.0030115599999973597, 
            "c0": -5.015625
        }, 
        {
            "c3": -2.739899981701009e-12, 
            "c2": 2.000000165480742e-11, 
            "c1": -0.0030115599999973597, 
            "c0": 2.35546875
        }
    ], 
    "decision": 1, 
    "ax": -0.10164035513130425, 
    "ay": 0.0632636337474756, 
    "objects": [
        {
            "theta": 0.05416173960621757, 
            "age": 20, 
            "v": 0.81605374671644, 
            "l": 4.832779, 
            "value": 51.60909677195453, 
            "reliability": 5, 
            "w": 2.171056, 
            "ax": -0.7714623063447851, 
            "y": 4.5285976506944685, 
            "x": 5.576818097273666, 
            "omega": 0.12401293048529209, 
            "id": 1
        }, 
        {
            "theta": 3.1722060746573137, 
            "age": 21, 
            "v": 0.7215436550019799, 
            "l": 4.239897, 
            "value": 336.46342724236416, 
            "reliability": 5, 
            "w": 2.178829, 
            "ax": -0.1329813412411966, 
            "y": 0.6628638244784922, 
            "x": 18.330958479920298, 
            "omega": 0.21189933376103723, 
            "id": 0
        }
    ], 
    "is_tunnel": false, 
    "v": 2.490321273936649, 
    "y": 126.7241097, 
    "x": 37.364956, 
    "omega": 0.006035752788022474, 
    "theta": 3.7885863351358235
}