{
    "deviation": 0.296875, 
    "lanes": [
        {
            "c3": -8.828965409999912e-07, 
            "c2": -0.00018164014000000145, 
            "c1": -0.0059412399999985155, 
            "c0": -1.35546875
        }, 
        {
            "c3": -8.828965409999912e-07, 
            "c2": -0.00018164014000000145, 
            "c1": -0.0059412399999985155, 
            "c0": 1.94921875
        }, 
        {
            "c3": -2.739899981701009e-12, 
            "c2": 2.000000165480742e-11, 
            "c1": -0.058675479999998004, 
            "c0": -2.15625
        }, 
        {
            "c3": -2.739899981701009e-12, 
            "c2": -0.0004189442200000018, 
            "c1": -0.008870919999999671, 
            "c0": 5.5234375
        }
    ], 
    "decision": 1, 
    "ax": -0.13407508868130424, 
    "ay": 0.09651254434747555, 
    "objects": [
        {
            "theta": 0.12255457961700846, 
            "age": 38, 
            "v": 1.846074730826454, 
            "l": 4.249892, 
            "value": 52.85787638205105, 
            "reliability": 5, 
            "w": 2.160034, 
            "ax": -0.21921537774311767, 
            "y": 3.441158422905034, 
            "x": 6.4043973245357595, 
            "omega": 0.05131115653833733, 
            "id": 27
        }, 
        {
            "theta": 0.10495018272754347, 
            "age": 38, 
            "v": 4.6810042496316004, 
            "l": 4.184772, 
            "value": 623.6648617720522, 
            "reliability": 5, 
            "w": 2.158753, 
            "ax": 0.5368108551466809, 
            "y": 4.537000184050867, 
            "x": 24.55769718646222, 
            "omega": 0.10653902367212242, 
            "id": 28
        }, 
        {
            "theta": 0.07370082858924032, 
            "age": 41, 
            "v": 4.757100518490622, 
            "l": 12, 
            "value": 891.8301312698297, 
            "reliability": 5, 
            "w": 2.371151, 
            "ax": 0.6867587896694795, 
            "y": -2.7291795220212562, 
            "x": 29.738555956979646, 
            "omega": 0.07438661673245678, 
            "id": 26
        }
    ], 
    "is_tunnel": false, 
    "v": 6.690904330916608, 
    "y": 126.7141052, 
    "x": 37.3677194, 
    "omega": 0.01162080639440433, 
    "theta": 3.8158134288563574
}