{
    "deviation": 1.6484375, 
    "lanes": [
        {
            "c3": 4.7310912820001396e-07, 
            "c2": -0.00011523406000000375, 
            "c1": 0.06046484000000163, 
            "c0": -0.01953125
        }, 
        {
            "c3": 4.7310912820001396e-07, 
            "c2": -0.00011523406000000375, 
            "c1": 0.06046484000000163, 
            "c0": 3.31640625
        }, 
        {
            "c3": -2.739899981701009e-12, 
            "c2": 2.000000165480742e-11, 
            "c1": 0.050699240000000145, 
            "c0": -3.3515625
        }, 
        {
            "c3": -2.739899981701009e-12, 
            "c2": 2.000000165480742e-11, 
            "c1": 0.029214920000001143, 
            "c0": 4.41015625
        }
    ], 
    "decision": 2, 
    "ax": 0.5016456888986958, 
    "ay": 0.16744355362747557, 
    "objects": [
        {
            "theta": 0.035406038258316674, 
            "age": 7, 
            "v": 13.00466977317499, 
            "l": 4.128182, 
            "value": 755.3741547193434, 
            "reliability": 5, 
            "w": 2.154686, 
            "ax": 0.2262607446847966, 
            "y": 1.5121596384888738, 
            "x": 27.44244026953632, 
            "omega": 0.9176036378820505, 
            "id": 31
        }, 
        {
            "theta": -0.09796907784530881, 
            "age": 148, 
            "v": 11.522861620468476, 
            "l": 12, 
            "value": 1035.577248788084, 
            "reliability": 5, 
            "w": 2.371151, 
            "ax": 0.48356048403315827, 
            "y": -5.66383744070023, 
            "x": 31.678039621059355, 
            "omega": -0.06254449572706766, 
            "id": 26
        }
    ], 
    "is_tunnel": false, 
    "v": 11.5, 
    "y": 126.7134881, 
    "x": 37.3670588, 
    "omega": 0.01650772829998845, 
    "theta": 3.724183643126655
}